simuOpt.py
simuPOP/__init__.py
simuPOP/_gsl.cpython-38-darwin.so
simuPOP/_simuPOP_ba.cpython-38-darwin.so
simuPOP/_simuPOP_baop.cpython-38-darwin.so
simuPOP/_simuPOP_la.cpython-38-darwin.so
simuPOP/_simuPOP_laop.cpython-38-darwin.so
simuPOP/_simuPOP_lin.cpython-38-darwin.so
simuPOP/_simuPOP_linop.cpython-38-darwin.so
simuPOP/_simuPOP_mu.cpython-38-darwin.so
simuPOP/_simuPOP_muop.cpython-38-darwin.so
simuPOP/_simuPOP_op.cpython-38-darwin.so
simuPOP/_simuPOP_std.cpython-38-darwin.so
simuPOP/demography.py
simuPOP/gsl.py
simuPOP/sampling.py
simuPOP/simuPOP_ba.py
simuPOP/simuPOP_baop.py
simuPOP/simuPOP_la.py
simuPOP/simuPOP_laop.py
simuPOP/simuPOP_lin.py
simuPOP/simuPOP_linop.py
simuPOP/simuPOP_mu.py
simuPOP/simuPOP_muop.py
simuPOP/simuPOP_op.py
simuPOP/simuPOP_std.py
simuPOP/utils.py
src/__init__.py
src/_version.py
src/demography.py
src/gsl.py
src/sampling.py
src/simuPOP_ba.py
src/simuPOP_baop.py
src/simuPOP_la.py
src/simuPOP_laop.py
src/simuPOP_lin.py
src/simuPOP_linop.py
src/simuPOP_mu.py
src/simuPOP_muop.py
src/simuPOP_op.py
src/simuPOP_std.py
src/utils.py
simuPOP-1.1.17.dist-info/AUTHORS
simuPOP-1.1.17.dist-info/COPYING
simuPOP-1.1.17.dist-info/METADATA
simuPOP-1.1.17.dist-info/WHEEL
simuPOP-1.1.17.dist-info/top_level.txt
simuPOP-1.1.17.dist-info/RECORD
