Metadata-Version: 2.1
Name: simuPOP
Version: 1.1.17
Summary: Forward-time population genetics simulation environment
Home-page: https://github.com/BoPeng/simuPOP
Author: Bo Peng
Author-email: Bo.Peng@bcm.edu
Maintainer: Bo Peng
Maintainer-email: Bo.Peng@bcm.edu
License: UNKNOWN
Download-URL: https://pypi.org/project/simuPOP/#files
Platform: all
Classifier: Development Status :: 5 - Production/Stable
Classifier: Environment :: Console
Classifier: Intended Audience :: Education
Classifier: Intended Audience :: Science/Research
Classifier: License :: OSI Approved :: GNU General Public License (GPL)
Classifier: Natural Language :: English
Classifier: Operating System :: OS Independent
Classifier: Programming Language :: C++
Classifier: Programming Language :: Python :: 3
Classifier: Topic :: Scientific/Engineering :: Bio-Informatics
License-File: COPYING
License-File: AUTHORS
Requires-Dist: setuptools
